pdfschedule.py
pdfschedule-0.4.1.dist-info/METADATA
pdfschedule-0.4.1.dist-info/WHEEL
pdfschedule-0.4.1.dist-info/entry_points.txt
pdfschedule-0.4.1.dist-info/licenses/LICENSE
pdfschedule-0.4.1.dist-info/RECORD
