Metadata-Version: 2.3
Name: pdfschedule
Version: 0.4.1
Summary: Weekly schedule typesetter
Project-URL: Source Code, https://github.com/jwodder/schedule
Project-URL: Bug Tracker, https://github.com/jwodder/schedule/issues
Author-email: John Thorvald Wodder II <pdfschedule@varonathe.org>
License: MIT
Keywords: pdf,schedule,week
Classifier: Environment :: Console
Classifier: Intended Audience :: End Users/Desktop
Classifier: License :: OSI Approved :: MIT License
Classifier: Programming Language :: Python :: 3
Classifier: Programming Language :: Python :: 3 :: Only
Classifier: Programming Language :: Python :: 3.8
Classifier: Programming Language :: Python :: 3.9
Classifier: Programming Language :: Python :: 3.10
Classifier: Programming Language :: Python :: 3.11
Classifier: Programming Language :: Python :: 3.12
Classifier: Programming Language :: Python :: 3.13
Classifier: Programming Language :: Python :: Implementation :: CPython
Classifier: Topic :: Office/Business :: Scheduling
Classifier: Topic :: Printing
Requires-Python: >=3.8
Requires-Dist: attrs>=18.2
Requires-Dist: click>=7.0
Requires-Dist: pyyaml<7.0,>=5.0
Requires-Dist: reportlab~=3.4
